Metadata-Version: 2.1
Name: MULTI_SESSION_SAP_GUI_LIBRARY
Version: 0.0.1
Summary: Lib teste
Author: Jose luis and Guillerme Manhaes
License: MIT License
Keywords: sap
License-File: LICENSE
